MANIFEST.in
README.md
pyproject.toml
requirements.txt
setup.py
lib/krisp_python_module.cpp
lib/cmake/CMakeLists.txt
lib/cmake/krisp.cmake
lib/cmake/krisp.third.party.linux.arm64.cmake
lib/cmake/krisp.third.party.linux.x64.cmake
lib/cmake/krisp.third.party.mac.arm.cmake
lib/cmake/krisp.third.party.mac.x64.cmake
lib/cmake/krisp.third.party.windows.x64.cmake
lib/cmake/mkl.cmake
lib/cmake/mkl.linux.cmake
lib/cmake/visualstudio.cmake
scripts/build.sh
scripts/clear.sh
scripts/clear_pycharm_cache.sh
scripts/prepare_dist.sh
scripts/run_example.sh
src/pipecat_ai_krisp.egg-info/PKG-INFO
src/pipecat_ai_krisp.egg-info/SOURCES.txt
src/pipecat_ai_krisp.egg-info/dependency_links.txt
src/pipecat_ai_krisp.egg-info/requires.txt
src/pipecat_ai_krisp.egg-info/top_level.txt
src/pipecat_ai_krisp/audio/__init__.py
src/pipecat_ai_krisp/audio/krisp_processor.py
src/pipecat_ai_krisp/audio/__pycache__/__init__.cpython-312.pyc
src/pipecat_ai_krisp/audio/__pycache__/krisp_processor.cpython-312.pyc