Metadata-Version: 2.1
Name: pipecat-ai-krisp
Version: 0.4.0
Summary: A package for pipecat krisp functionality
License: BSD 2-Clause License
Project-URL: Home, https://github.com/pipecat-ai/pipecat-krisp
Requires-Dist: numpy
